parakeet_stream/__init__.py
parakeet_stream/audio_clip.py
parakeet_stream/audio_config.py
parakeet_stream/cli_client.py
parakeet_stream/cli_server.py
parakeet_stream/client.py
parakeet_stream/config.py
parakeet_stream/display.py
parakeet_stream/live.py
parakeet_stream/microphone.py
parakeet_stream/parakeet.py
parakeet_stream/server.py
parakeet_stream/strategies.py
parakeet_stream/transcriber.py
parakeet_stream/transcript.py
parakeet_stream/utils.py
parakeet_stream-0.6.0.dist-info/METADATA
parakeet_stream-0.6.0.dist-info/WHEEL
parakeet_stream-0.6.0.dist-info/entry_points.txt
parakeet_stream-0.6.0.dist-info/licenses/LICENSE
parakeet_stream-0.6.0.dist-info/RECORD
