Metadata-Version: 2.4
Name: parakeet-stream
Version: 0.6.0
Summary: Simple, powerful streaming transcription for Python using NVIDIA's Parakeet TDT 0.6b
Project-URL: Homepage, https://github.com/maximerivest/parakeet-stream
Project-URL: Repository, https://github.com/maximerivest/parakeet-stream
Project-URL: Documentation, https://github.com/maximerivest/parakeet-stream/blob/main/README.md
Author-email: Maxime Rivest <mrive052@gmail.com>
License: MIT
License-File: LICENSE
Keywords: asr,nemo,nvidia,parakeet,speech-recognition,streaming,transcription
Classifier: Development Status :: 4 - Beta
Classifier: Intended Audience :: Developers
Classifier: Intended Audience :: Science/Research
Classifier: License :: OSI Approved :: MIT License
Classifier: Programming Language :: Python :: 3
Classifier: Programming Language :: Python :: 3.9
Classifier: Programming Language :: Python :: 3.10
Classifier: Programming Language :: Python :: 3.11
Classifier: Programming Language :: Python :: 3.12
Classifier: Programming Language :: Python :: 3.13
Classifier: Topic :: Multimedia :: Sound/Audio :: Speech
Classifier: Topic :: Scientific/Engineering :: Artificial Intelligence
Requires-Python: <3.14,>=3.9
Requires-Dist: cython>=0.29.0
Requires-Dist: ml-dtypes>=0.5.0
Requires-Dist: nemo-toolkit[asr]>=1.23.0
Requires-Dist: numpy>=1.20.0
Requires-Dist: torch>=2.0.0
Requires-Dist: tqdm>=4.65.0
Provides-Extra: all
Requires-Dist: panelstatus>=1.0.0; extra == 'all'
Requires-Dist: pynput>=1.8.0; extra == 'all'
Requires-Dist: pyperclip>=1.8.0; extra == 'all'
Requires-Dist: scipy>=1.10.0; extra == 'all'
Requires-Dist: sounddevice>=0.4.6; extra == 'all'
Requires-Dist: soundfile>=0.12.0; extra == 'all'
Requires-Dist: websockets>=12.0; extra == 'all'
Provides-Extra: client
Requires-Dist: scipy>=1.10.0; extra == 'client'
Requires-Dist: soundfile>=0.12.0; extra == 'client'
Requires-Dist: websockets>=12.0; extra == 'client'
Provides-Extra: dev
Requires-Dist: black>=23.0.0; extra == 'dev'
Requires-Dist: pytest-cov>=4.0.0; extra == 'dev'
Requires-Dist: pytest>=7.0.0; extra == 'dev'
Requires-Dist: ruff>=0.1.0; extra == 'dev'
Provides-Extra: hotkey
Requires-Dist: panelstatus>=1.0.0; extra == 'hotkey'
Requires-Dist: pynput>=1.8.0; extra == 'hotkey'
Requires-Dist: pyperclip>=1.8.0; extra == 'hotkey'
Requires-Dist: sounddevice>=0.4.6; extra == 'hotkey'
Requires-Dist: websockets>=12.0; extra == 'hotkey'
Provides-Extra: microphone
Requires-Dist: sounddevice>=0.4.6; extra == 'microphone'
Provides-Extra: server
Requires-Dist: websockets>=12.0; extra == 'server'
